profileclassifier/__init__.py
profileclassifier/lista_deputados.csv
profileclassifier/lista_governadores.csv
profileclassifier/lista_midia_partidaria.csv
profileclassifier/lista_midia_trad.csv
profileclassifier/lista_ministros.csv
profileclassifier/lista_org.csv
profileclassifier/lista_politico.csv
profileclassifier/lista_prefeitos.csv
profileclassifier/lista_senadores.csv
profileclassifier/lista_unifederal.csv
profileclassifier/ner_data.csv
profileclassifier/nlpclassifier_profilener.py
ProfileNER_classifier-0.7.7.dist-info/LICENCE.txt
ProfileNER_classifier-0.7.7.dist-info/METADATA
ProfileNER_classifier-0.7.7.dist-info/WHEEL
ProfileNER_classifier-0.7.7.dist-info/top_level.txt
ProfileNER_classifier-0.7.7.dist-info/RECORD
