Metadata-Version: 2.1
Name: ProfileNER-classifier
Version: 0.7.7
Summary: Performs Classification using Regex for social media user's profile categorization and NER tasks
Home-page: UNKNOWN
Author: Arthur Lopes
Author-email: arthurdslopes@gmail.com
License: MIT
Keywords: NER,profile categories,classification,social media
Platform: UNKNOWN
Classifier: Development Status :: 5 - Production/Stable
Classifier: Intended Audience :: Science/Research
Classifier: Operating System :: Microsoft :: Windows :: Windows 10
Classifier: License :: OSI Approved :: MIT License
Classifier: Programming Language :: Python :: 3
